swimstroke/__init__.py
swimstroke/__main__.py
swimstroke/ev3.py
swimstroke/helpers.py
swimstroke/hy3.py
swimstroke/scb.py
swimstroke/sd3.py
swimstroke/util.py
swimstroke/yaml.py
swimstroke-0.1.6.dist-info/licenses/LICENSE
swimstroke-0.1.6.dist-info/METADATA
swimstroke-0.1.6.dist-info/WHEEL
swimstroke-0.1.6.dist-info/top_level.txt
swimstroke-0.1.6.dist-info/RECORD
