Metadata-Version: 2.4
Name: swimstroke
Version: 0.1.6
License-File: LICENSE
Requires-Dist: PyYAML>=6.0.1
Dynamic: license-file
